icon_validator/__init__.py
icon_validator/__main__.py
icon_validator/constants.py
icon_validator/exceptions.py
icon_validator/styling.py
icon_validator/timing.py
icon_validator/validate.py
icon_validator/rules/__init__.py
icon_validator/rules/validator.py
icon_validator/rules/lists/__init__.py
icon_validator/rules/lists/lists.py
icon_validator/rules/lists/valid_data_types.py
icon_validator/rules/plugin_validators/__init__.py
icon_validator/rules/plugin_validators/acronym_validator.py
icon_validator/rules/plugin_validators/changelog_validator.py
icon_validator/rules/plugin_validators/cloud_ready_connection_credential_token_validator.py
icon_validator/rules/plugin_validators/cloud_ready_validator.py
icon_validator/rules/plugin_validators/confidential_validator.py
icon_validator/rules/plugin_validators/credentials_validator.py
icon_validator/rules/plugin_validators/default_value_validator.py
icon_validator/rules/plugin_validators/description_validator.py
icon_validator/rules/plugin_validators/docker_validator.py
icon_validator/rules/plugin_validators/dockerfile_parent_validator.py
icon_validator/rules/plugin_validators/encoding_validator.py
icon_validator/rules/plugin_validators/example_input_validator.py
icon_validator/rules/plugin_validators/exception_validator.py
icon_validator/rules/plugin_validators/exclude_product_validator.py
icon_validator/rules/plugin_validators/files_validator.py
icon_validator/rules/plugin_validators/help_example_validator.py
icon_validator/rules/plugin_validators/help_input_output_validator.py
icon_validator/rules/plugin_validators/help_validator.py
icon_validator/rules/plugin_validators/icon_validator.py
icon_validator/rules/plugin_validators/json_validator.py
icon_validator/rules/plugin_validators/name_validator.py
icon_validator/rules/plugin_validators/output_validator.py
icon_validator/rules/plugin_validators/password_validator.py
icon_validator/rules/plugin_validators/print_validator.py
insightconnect_integrations_validators-2.47.28.dist-info/LICENSE
insightconnect_integrations_validators-2.47.28.dist-info/METADATA
insightconnect_integrations_validators-2.47.28.dist-info/WHEEL
insightconnect_integrations_validators-2.47.28.dist-info/entry_points.txt
insightconnect_integrations_validators-2.47.28.dist-info/top_level.txt
insightconnect_integrations_validators-2.47.28.dist-info/RECORD
