Metadata-Version: 2.1
Name: insightconnect-integrations-validators
Version: 2.47.28
Summary: Validator tooling for InsightConnect integrations
Home-page: https://github.com/rapid7/icon-integrations-validators
Author: Rapid7 Integrations Alliance
Author-email: integrationalliance@rapid7.com
License: MIT
Classifier: Programming Language :: Python :: 3
Classifier: Operating System :: OS Independent
Classifier: Intended Audience :: Developers
Classifier: License :: OSI Approved :: MIT License
Classifier: Natural Language :: English
Classifier: Topic :: Software Development :: Build Tools
License-File: LICENSE
Requires-Dist: jsonschema==2.3.0
Requires-Dist: validators==0.22.0
Requires-Dist: filetype==1.0.5
Requires-Dist: insightconnect-integrations-plugin-spec-tooling==1.3.2
Requires-Dist: requests==2.32.2
Requires-Dist: urlextract==0.14.0
Requires-Dist: typing==3.7.4.1
Requires-Dist: PyYAML==6.0.1
Requires-Dist: dacite==1.6.0
Requires-Dist: GitPython==3.1.41
